rlxcrypt/__init__.py
rlxcrypt/loader.cpython-310-x86_64-linux-gnu.so
rlxcrypt/main.py
rlxcrypt-0.0.7.dist-info/METADATA
rlxcrypt-0.0.7.dist-info/WHEEL
rlxcrypt-0.0.7.dist-info/entry_points.txt
rlxcrypt-0.0.7.dist-info/top_level.txt
rlxcrypt-0.0.7.dist-info/RECORD
rlxcrypt-0.0.7.dist-info/licenses/LICENSE.txt
