Metadata-Version: 2.4
Name: rlxcrypt
Version: 0.0.7
Summary: seamlessly encrypt, distribute and load python modules
Home-page: https://github.com/rramosp/rlxcrypt/
Author: rramosp
Author-email: rramosp@unal.edu.co
License: MIT
Platform: any
Classifier: Development Status :: 4 - Beta
Classifier: Programming Language :: Python
License-File: LICENSE.txt
Requires-Dist: importlib-metadata; python_version < "3.8"
Requires-Dist: imphook
Requires-Dist: cython
Requires-Dist: pycryptodome
Requires-Dist: cryptography
Provides-Extra: testing
Requires-Dist: setuptools; extra == "testing"
Requires-Dist: pytest; extra == "testing"
Requires-Dist: pytest-cov; extra == "testing"
Dynamic: license-file
